Metadata-Version: 2.4
Name: tobias
Version: 0.17.2
Summary: Transcription factor Occupancy prediction By Investigation of ATAC-seq Signal
Home-page: https://github.com/loosolab/TOBIAS
Author: Mette Bentsen
Author-email: mette.bentsen@mpi-bn.mpg.de
License: MIT
Classifier: License :: OSI Approved :: MIT License
Classifier: Intended Audience :: Science/Research
Classifier: Topic :: Scientific/Engineering :: Bio-Informatics
Classifier: Programming Language :: Python :: 3
License-File: LICENSE
Requires-Dist: numpy
Requires-Dist: scipy
Requires-Dist: pysam
Requires-Dist: pybedtools
Requires-Dist: matplotlib>=2
Requires-Dist: scikit-learn
Requires-Dist: pandas
Requires-Dist: pypdf2>=1.28.0
Requires-Dist: xlsxwriter
Requires-Dist: adjustText>=0.8
Requires-Dist: pyBigWig>=0.3
Requires-Dist: MOODS-python
Requires-Dist: svist4get>=1.2.24
Requires-Dist: logomaker
Requires-Dist: seaborn>=0.9.1
Requires-Dist: boto3
Requires-Dist: pyyaml>5.1
Requires-Dist: kneed
Dynamic: author
Dynamic: author-email
Dynamic: classifier
Dynamic: description
Dynamic: description-content-type
Dynamic: home-page
Dynamic: license
Dynamic: license-file
Dynamic: requires-dist
Dynamic: summary
